[
  {
    "ID": "jrV1KXr7yszb8pfqWm6YCQ==",
    "Path": "save:Resource/Images/152.png",
    "Name": "152.png",
    "Type": 1
  },
  {
    "ID": "PkaqtPPgztxGsg4XGggXHA==",
    "Path": "save:Resource/Images/153.png",
    "Name": "153.png",
    "Type": 1
  },
  {
    "ID": "qeGVTEHc9ihouYAJbGjn6A==",
    "Path": "save:Resource/Images/154.png",
    "Name": "154.png",
    "Type": 1
  },
  {
    "ID": "UULKmoqUhpACGNVNvUMD7Q==",
    "Path": "save:Resource/Images/155.png",
    "Name": "155.png",
    "Type": 1
  },
  {
    "ID": "vcem9S4ExbW0PxGnXnQUAA==",
    "Path": "save:Resource/Images/156.png",
    "Name": "156.png",
    "Type": 1
  },
  {
    "ID": "swKX9HlXPGGcKPe5LZd2xQ==",
    "Path": "save:Resource/Images/157.png",
    "Name": "157.png",
    "Type": 1
  },
  {
    "ID": "5CO+WiiAKLmVKHmZ8tqAaA==",
    "Path": "save:Resource/Images/158.png",
    "Name": "158.png",
    "Type": 1
  },
  {
    "ID": "UH2dhsoSnCBgG7jbaAE4cg==",
    "Path": "save:Resource/Images/159.png",
    "Name": "159.png",
    "Type": 1
  },
  {
    "ID": "//mS/bhsss0nC+Tiz2buQg==",
    "Path": "save:Resource/Images/160.png",
    "Name": "160.png",
    "Type": 1
  },
  {
    "ID": "P6KX2+UuA9P/UGiz/LGbGQ==",
    "Path": "save:Resource/Images/161.png",
    "Name": "161.png",
    "Type": 1
  },
  {
    "ID": "ntA4bmG1BRBvodPHut2vIg==",
    "Path": "save:Resource/Images/162.png",
    "Name": "162.png",
    "Type": 1
  },
  {
    "ID": "6poarl5Ns9CJ1u+SOzsVog==",
    "Path": "save:Resource/Images/163.png",
    "Name": "163.png",
    "Type": 1
  },
  {
    "ID": "s4f6pNaHdJDLFJe7IpAloA==",
    "Path": "save:Resource/Images/164.png",
    "Name": "164.png",
    "Type": 1
  },
  {
    "ID": "w9+xRheiuZxhKKU+IoErbQ==",
    "Path": "save:Resource/Images/165.png",
    "Name": "165.png",
    "Type": 1
  },
  {
    "ID": "B3xFEmn3QjMGkiE0+RtbzQ==",
    "Path": "save:Resource/Images/166.png",
    "Name": "166.png",
    "Type": 1
  },
  {
    "ID": "82HLxvDLvKjvbuh+6sSDdQ==",
    "Path": "save:Resource/Images/167.png",
    "Name": "167.png",
    "Type": 1
  },
  {
    "ID": "2/D+vzsZRI/iH7W6pBnrCA==",
    "Path": "save:Resource/Images/168.png",
    "Name": "168.png",
    "Type": 1
  },
  {
    "ID": "LH37jIhMguxdeFQvd5ODWg==",
    "Path": "save:Resource/Images/169.png",
    "Name": "169.png",
    "Type": 1
  },
  {
    "ID": "GH8SxDcgqrHAdPkqHQDdPQ==",
    "Path": "save:Resource/Images/170.png",
    "Name": "170.png",
    "Type": 1
  },
  {
    "ID": "fAXP561oRMpAyHNHqC4mEA==",
    "Path": "save:Resource/Images/171.png",
    "Name": "171.png",
    "Type": 1
  },
  {
    "ID": "EtHggIWAL+UM5ILhnXnhXg==",
    "Path": "save:Resource/Images/172.png",
    "Name": "172.png",
    "Type": 1
  },
  {
    "ID": "0TcfhiBOgTMeQ0uMECXyuw==",
    "Path": "save:Resource/Images/173.png",
    "Name": "173.png",
    "Type": 1
  },
  {
    "ID": "v0L494ObrJ/zlhntJAuZow==",
    "Path": "save:Resource/Images/174.png",
    "Name": "174.png",
    "Type": 1
  },
  {
    "ID": "Eh7jhg4/Xxn8AqoK3OHxMw==",
    "Path": "save:Resource/Images/175.png",
    "Name": "175.png",
    "Type": 1
  },
  {
    "ID": "K64v3/gkh8O3Soa7pWwTbg==",
    "Path": "save:Resource/Images/176.png",
    "Name": "176.png",
    "Type": 1
  },
  {
    "ID": "aNNH+YfTBCwfzJ3qGFv+kA==",
    "Path": "save:Resource/Images/177.png",
    "Name": "177.png",
    "Type": 1
  },
  {
    "ID": "TDUZt8HU5N6PSfvEDA21Aw==",
    "Path": "save:Resource/Images/178.png",
    "Name": "178.png",
    "Type": 1
  },
  {
    "ID": "zSpLN48zANsLXjWTFVlwpQ==",
    "Path": "save:Resource/Images/179.png",
    "Name": "179.png",
    "Type": 1
  },
  {
    "ID": "Rkhrz9+X6uSS2VFGeinEPA==",
    "Path": "save:Resource/Images/180.png",
    "Name": "180.png",
    "Type": 1
  },
  {
    "ID": "uT6dmvRmUGqERkZRZFgl9g==",
    "Path": "save:Resource/Images/181.png",
    "Name": "181.png",
    "Type": 1
  },
  {
    "ID": "HfoFNgzVQ4pKby946A6l5w==",
    "Path": "save:Resource/Images/181mega.png",
    "Name": "181mega.png",
    "Type": 1
  },
  {
    "ID": "Fm8aup1Mc54bFZUDnmW45Q==",
    "Path": "save:Resource/Images/182.png",
    "Name": "182.png",
    "Type": 1
  },
  {
    "ID": "2nFWMB8bfFRRWJ4uA40O+g==",
    "Path": "save:Resource/Images/183.png",
    "Name": "183.png",
    "Type": 1
  },
  {
    "ID": "Nq82K9cqJspOniSFYkDfGQ==",
    "Path": "save:Resource/Images/184.png",
    "Name": "184.png",
    "Type": 1
  },
  {
    "ID": "eu0nzdNDJeXLe1CmVhSc/g==",
    "Path": "save:Resource/Images/185.png",
    "Name": "185.png",
    "Type": 1
  },
  {
    "ID": "S05yZE/gd3+u1Pbtk7FbTA==",
    "Path": "save:Resource/Images/186.png",
    "Name": "186.png",
    "Type": 1
  },
  {
    "ID": "OVLvhKHGAFefor1/CE0cnw==",
    "Path": "save:Resource/Images/187.png",
    "Name": "187.png",
    "Type": 1
  },
  {
    "ID": "MzWnzQZpYCttx2XLobfdhw==",
    "Path": "save:Resource/Images/188.png",
    "Name": "188.png",
    "Type": 1
  },
  {
    "ID": "uzR9SG9zTzAGbw7nPclHCw==",
    "Path": "save:Resource/Images/189.png",
    "Name": "189.png",
    "Type": 1
  },
  {
    "ID": "4M3d7b0gC2dTOiT95PADgA==",
    "Path": "save:Resource/Images/190.png",
    "Name": "190.png",
    "Type": 1
  },
  {
    "ID": "DBKxXPN1Gwy8dLRCBfvBjw==",
    "Path": "save:Resource/Images/191.png",
    "Name": "191.png",
    "Type": 1
  },
  {
    "ID": "M0/jA9Hpbs/FW08hmBYFUA==",
    "Path": "save:Resource/Images/192.png",
    "Name": "192.png",
    "Type": 1
  },
  {
    "ID": "+GWBX4PgvUMuB1CSIPUftQ==",
    "Path": "save:Resource/Images/193.png",
    "Name": "193.png",
    "Type": 1
  },
  {
    "ID": "KmMHIdmVQV2QYBjXIrEvLw==",
    "Path": "save:Resource/Images/194.png",
    "Name": "194.png",
    "Type": 1
  },
  {
    "ID": "kaDmjg8ueA7fcRaO1Xh7Dw==",
    "Path": "save:Resource/Images/195.png",
    "Name": "195.png",
    "Type": 1
  },
  {
    "ID": "bckVmMnkiUd0c0DXzdzvxA==",
    "Path": "save:Resource/Images/196.png",
    "Name": "196.png",
    "Type": 1
  },
  {
    "ID": "NXZ2z2yr58gSVjDsvGXskg==",
    "Path": "save:Resource/Images/197.png",
    "Name": "197.png",
    "Type": 1
  },
  {
    "ID": "HDn+G/F20K7PqFRSCawigA==",
    "Path": "save:Resource/Images/198.png",
    "Name": "198.png",
    "Type": 1
  },
  {
    "ID": "0XHme/cbKwMnuexvdtZY/w==",
    "Path": "save:Resource/Images/199.png",
    "Name": "199.png",
    "Type": 1
  },
  {
    "ID": "SM+ZlXn5TpFvCOQwLAPGQg==",
    "Path": "save:Resource/Images/200.png",
    "Name": "200.png",
    "Type": 1
  },
  {
    "ID": "xI2pu8tOUCN9PDRnPtvFbw==",
    "Path": "save:Resource/Images/201.png",
    "Name": "201.png",
    "Type": 1
  },
  {
    "ID": "6xQxm5ZfKqDAdN9yBqOJXQ==",
    "Path": "save:Resource/Images/202.png",
    "Name": "202.png",
    "Type": 1
  },
  {
    "ID": "ZUFeTJFTY702OWGX9KZyEQ==",
    "Path": "save:Resource/Images/203.png",
    "Name": "203.png",
    "Type": 1
  },
  {
    "ID": "KdSJWl+FYCo6Zj365YVnVA==",
    "Path": "save:Resource/Images/204.png",
    "Name": "204.png",
    "Type": 1
  },
  {
    "ID": "7OE2g/KP9xQEmhGvpjJTEQ==",
    "Path": "save:Resource/Images/205.png",
    "Name": "205.png",
    "Type": 1
  },
  {
    "ID": "OCizIxlWVebr63E7sNj7xw==",
    "Path": "save:Resource/Images/206.png",
    "Name": "206.png",
    "Type": 1
  },
  {
    "ID": "jmcSoF6qpQw9nUHb5ZSKWQ==",
    "Path": "save:Resource/Images/207.png",
    "Name": "207.png",
    "Type": 1
  },
  {
    "ID": "7RA3F8PmJp5HRvYUvkdObg==",
    "Path": "save:Resource/Images/208.png",
    "Name": "208.png",
    "Type": 1
  },
  {
    "ID": "tOHmjD6F9ngP5zb7mtrE3Q==",
    "Path": "save:Resource/Images/209.png",
    "Name": "209.png",
    "Type": 1
  },
  {
    "ID": "xJfLrP6SIVpyPU3eQaEjhQ==",
    "Path": "save:Resource/Images/210.png",
    "Name": "210.png",
    "Type": 1
  },
  {
    "ID": "P6NQiqNDJyIIe+ZKHaVVMQ==",
    "Path": "save:Resource/Images/211.png",
    "Name": "211.png",
    "Type": 1
  },
  {
    "ID": "lqF6QSdDAG4BsXJh/CvnjA==",
    "Path": "save:Resource/Images/212.png",
    "Name": "212.png",
    "Type": 1
  },
  {
    "ID": "k95zXLhR9idFp6LPCvYmuw==",
    "Path": "save:Resource/Images/213.png",
    "Name": "213.png",
    "Type": 1
  },
  {
    "ID": "jfAHm3fsu8fvj3vPi22Y0A==",
    "Path": "save:Resource/Images/214.png",
    "Name": "214.png",
    "Type": 1
  },
  {
    "ID": "+9VMTHmRJLHvubogcHdtEw==",
    "Path": "save:Resource/Images/214mega.png",
    "Name": "214mega.png",
    "Type": 1
  },
  {
    "ID": "IGn+yP73ATbrba7J/o83vA==",
    "Path": "save:Resource/Images/215.png",
    "Name": "215.png",
    "Type": 1
  },
  {
    "ID": "G2fttj4Z9Zx/S2lMbio5sA==",
    "Path": "save:Resource/Images/216.png",
    "Name": "216.png",
    "Type": 1
  },
  {
    "ID": "NSUukL5Q+cj/61KQg0CNRQ==",
    "Path": "save:Resource/Images/217.png",
    "Name": "217.png",
    "Type": 1
  },
  {
    "ID": "uaVRyH9MXxyYb1iQDqETxw==",
    "Path": "save:Resource/Images/218.png",
    "Name": "218.png",
    "Type": 1
  },
  {
    "ID": "3JAnpfbLDgJCT2NZdUFK5Q==",
    "Path": "save:Resource/Images/219.png",
    "Name": "219.png",
    "Type": 1
  },
  {
    "ID": "/UFrcwW0cKJtv1ThxIiVdg==",
    "Path": "save:Resource/Images/220.png",
    "Name": "220.png",
    "Type": 1
  },
  {
    "ID": "E/V4b5vbhPgro0G8CJoQxg==",
    "Path": "save:Resource/Images/221.png",
    "Name": "221.png",
    "Type": 1
  },
  {
    "ID": "vuC1bwVgocnwXkJpA9DRWw==",
    "Path": "save:Resource/Images/222.png",
    "Name": "222.png",
    "Type": 1
  },
  {
    "ID": "/V+O1GH+tTeogdbes73CXg==",
    "Path": "save:Resource/Images/223.png",
    "Name": "223.png",
    "Type": 1
  },
  {
    "ID": "oR+y6mtotKxweg0ADunn6A==",
    "Path": "save:Resource/Images/224.png",
    "Name": "224.png",
    "Type": 1
  },
  {
    "ID": "aaJqrfdN4SAIOtXS6oBNng==",
    "Path": "save:Resource/Images/225.png",
    "Name": "225.png",
    "Type": 1
  },
  {
    "ID": "eimtnsXdcQYbw3iwv9Ka8A==",
    "Path": "save:Resource/Images/226.png",
    "Name": "226.png",
    "Type": 1
  },
  {
    "ID": "gY0A7eT3cTcpgSYtw3XE5g==",
    "Path": "save:Resource/Images/227.png",
    "Name": "227.png",
    "Type": 1
  },
  {
    "ID": "m23+RztVXV9Tb5+dS1uZgQ==",
    "Path": "save:Resource/Images/228.png",
    "Name": "228.png",
    "Type": 1
  },
  {
    "ID": "BUXfjsuQkuIn6NFS/LFUNQ==",
    "Path": "save:Resource/Images/229.png",
    "Name": "229.png",
    "Type": 1
  },
  {
    "ID": "JWqH26KaT9ZbjGowlLk3ug==",
    "Path": "save:Resource/Images/230.png",
    "Name": "230.png",
    "Type": 1
  },
  {
    "ID": "kILyt+zHlw6pD94xvf/STA==",
    "Path": "save:Resource/Images/231.png",
    "Name": "231.png",
    "Type": 1
  },
  {
    "ID": "RAfHuhnQUvEW3k2ENuNlag==",
    "Path": "save:Resource/Images/232.png",
    "Name": "232.png",
    "Type": 1
  },
  {
    "ID": "E4bOBtHIh3P+RHfohYUtXw==",
    "Path": "save:Resource/Images/233.png",
    "Name": "233.png",
    "Type": 1
  },
  {
    "ID": "niKfRRag7TGG/FkN+m/PxA==",
    "Path": "save:Resource/Images/234.png",
    "Name": "234.png",
    "Type": 1
  },
  {
    "ID": "W/0yWxRncQxJI2Tm2S+qJA==",
    "Path": "save:Resource/Images/235.png",
    "Name": "235.png",
    "Type": 1
  },
  {
    "ID": "hWm7gZYYdZDmbN6m3AYtag==",
    "Path": "save:Resource/Images/236.png",
    "Name": "236.png",
    "Type": 1
  },
  {
    "ID": "g2E6D1/NQCz4hPBXRB/p5Q==",
    "Path": "save:Resource/Images/237.png",
    "Name": "237.png",
    "Type": 1
  },
  {
    "ID": "RsCqdTG/sF+hnt2lvWx07A==",
    "Path": "save:Resource/Images/238.png",
    "Name": "238.png",
    "Type": 1
  },
  {
    "ID": "Uj3sPe2Ssdy6axDEeUPE7w==",
    "Path": "save:Resource/Images/239.png",
    "Name": "239.png",
    "Type": 1
  },
  {
    "ID": "6PSQmtpjxomyRXY9G6ow3Q==",
    "Path": "save:Resource/Images/240.png",
    "Name": "240.png",
    "Type": 1
  },
  {
    "ID": "gco1ZAIyrVcRVkddKfDG3g==",
    "Path": "save:Resource/Images/241.png",
    "Name": "241.png",
    "Type": 1
  },
  {
    "ID": "uGa23CWpwaVYGAXEN9lngw==",
    "Path": "save:Resource/Images/242.png",
    "Name": "242.png",
    "Type": 1
  },
  {
    "ID": "2tLtJiiyV6Vbmh2BTHl8nQ==",
    "Path": "save:Resource/Images/243.png",
    "Name": "243.png",
    "Type": 1
  },
  {
    "ID": "ok6CrQzvWnr6ROrflzfkpQ==",
    "Path": "save:Resource/Images/244.png",
    "Name": "244.png",
    "Type": 1
  },
  {
    "ID": "0Y8gfvIunPBn4OQY1adA8g==",
    "Path": "save:Resource/Images/245.png",
    "Name": "245.png",
    "Type": 1
  },
  {
    "ID": "besG3bRNQ3qrri7lpljfbw==",
    "Path": "save:Resource/Images/246.png",
    "Name": "246.png",
    "Type": 1
  },
  {
    "ID": "G3pYXddpmX6/s24Cx2RYWw==",
    "Path": "save:Resource/Images/247.png",
    "Name": "247.png",
    "Type": 1
  },
  {
    "ID": "Ielc1fki98VdZLRpkhHRrA==",
    "Path": "save:Resource/Images/248.png",
    "Name": "248.png",
    "Type": 1
  },
  {
    "ID": "iIFLn5wyjH0nSmYadblKDw==",
    "Path": "save:Resource/Images/248mega.png",
    "Name": "248mega.png",
    "Type": 1
  },
  {
    "ID": "Htrppr5Dioa0kGCr2rwpeg==",
    "Path": "save:Resource/Images/249.png",
    "Name": "249.png",
    "Type": 1
  },
  {
    "ID": "cXsIdI7Tsw5hy+fJjC3b4w==",
    "Path": "save:Resource/Images/250.png",
    "Name": "250.png",
    "Type": 1
  },
  {
    "ID": "A2JHC/iw+zqpWMrtfObgrQ==",
    "Path": "save:Resource/Images/251.png",
    "Name": "251.png",
    "Type": 1
  },
  {
    "ID": "SjYOKoL97PrQOnvCszZ5GQ==",
    "Path": "save:Resource/Images/Tokens_152.png",
    "Name": "Tokens_152.png",
    "Type": 1
  },
  {
    "ID": "Jj0U57/hWXj6TfLR08Sadg==",
    "Path": "save:Resource/Images/Tokens_153.png",
    "Name": "Tokens_153.png",
    "Type": 1
  },
  {
    "ID": "F0csUv0T45zFcwVhdSsnnA==",
    "Path": "save:Resource/Images/Tokens_154.png",
    "Name": "Tokens_154.png",
    "Type": 1
  },
  {
    "ID": "DLGXbDVyJi9sTFS+uUri0w==",
    "Path": "save:Resource/Images/Tokens_155.png",
    "Name": "Tokens_155.png",
    "Type": 1
  },
  {
    "ID": "xZzmFu8bi3b1FFAblp3jMQ==",
    "Path": "save:Resource/Images/Tokens_156.png",
    "Name": "Tokens_156.png",
    "Type": 1
  },
  {
    "ID": "9XTIPXTlAjrRBUzvd24voQ==",
    "Path": "save:Resource/Images/Tokens_157.png",
    "Name": "Tokens_157.png",
    "Type": 1
  },
  {
    "ID": "KqNcBxulIYBR7pVS0GxecQ==",
    "Path": "save:Resource/Images/Tokens_158.png",
    "Name": "Tokens_158.png",
    "Type": 1
  },
  {
    "ID": "b5Mk3rdlWPgrKcgt6t+pLQ==",
    "Path": "save:Resource/Images/Tokens_159.png",
    "Name": "Tokens_159.png",
    "Type": 1
  },
  {
    "ID": "GzZWL2QZ1OxLcaVn8WW7Xg==",
    "Path": "save:Resource/Images/Tokens_160.png",
    "Name": "Tokens_160.png",
    "Type": 1
  },
  {
    "ID": "WqvKvWXY6FK31R8pWIHM8w==",
    "Path": "save:Resource/Images/Tokens_161.png",
    "Name": "Tokens_161.png",
    "Type": 1
  },
  {
    "ID": "pwzbbA4MXSjNTeMgO6A6Og==",
    "Path": "save:Resource/Images/Tokens_162.png",
    "Name": "Tokens_162.png",
    "Type": 1
  },
  {
    "ID": "J+LvmOXqGzbJUrjR7tzqcg==",
    "Path": "save:Resource/Images/Tokens_163.png",
    "Name": "Tokens_163.png",
    "Type": 1
  },
  {
    "ID": "9fqqU90RIAr9AORDZE+ltg==",
    "Path": "save:Resource/Images/Tokens_164.png",
    "Name": "Tokens_164.png",
    "Type": 1
  },
  {
    "ID": "d7lMkd4xj8mB9smzcS9l1A==",
    "Path": "save:Resource/Images/Tokens_165.png",
    "Name": "Tokens_165.png",
    "Type": 1
  },
  {
    "ID": "Mo69+vYggEptQ7hRsXIJ+g==",
    "Path": "save:Resource/Images/Tokens_166.png",
    "Name": "Tokens_166.png",
    "Type": 1
  },
  {
    "ID": "zNAxUAxs/h0ZApiNq6grEA==",
    "Path": "save:Resource/Images/Tokens_167.png",
    "Name": "Tokens_167.png",
    "Type": 1
  },
  {
    "ID": "FSgYHEGRvCsXFYlvuerBQQ==",
    "Path": "save:Resource/Images/Tokens_168.png",
    "Name": "Tokens_168.png",
    "Type": 1
  },
  {
    "ID": "sPTEpzDiiUIKF9m/4dOHcA==",
    "Path": "save:Resource/Images/Tokens_169.png",
    "Name": "Tokens_169.png",
    "Type": 1
  },
  {
    "ID": "arBTr18jhbBJsXZVopq/JA==",
    "Path": "save:Resource/Images/Tokens_170.png",
    "Name": "Tokens_170.png",
    "Type": 1
  },
  {
    "ID": "5ocyxIHCC04rmU23nRBE0A==",
    "Path": "save:Resource/Images/Tokens_171.png",
    "Name": "Tokens_171.png",
    "Type": 1
  },
  {
    "ID": "BiVdO0EMjzIYnQaouooPbg==",
    "Path": "save:Resource/Images/Tokens_172.png",
    "Name": "Tokens_172.png",
    "Type": 1
  },
  {
    "ID": "pyUbXjDDCW3mdnBGgKobVw==",
    "Path": "save:Resource/Images/Tokens_173.png",
    "Name": "Tokens_173.png",
    "Type": 1
  },
  {
    "ID": "UUjKXjoA/XW4TU+IkaTb9g==",
    "Path": "save:Resource/Images/Tokens_174.png",
    "Name": "Tokens_174.png",
    "Type": 1
  },
  {
    "ID": "3SnCFHvKReB2MSkIoGTH6Q==",
    "Path": "save:Resource/Images/Tokens_175.png",
    "Name": "Tokens_175.png",
    "Type": 1
  },
  {
    "ID": "NaRqJnqKljKNWvO0DV7dPQ==",
    "Path": "save:Resource/Images/Tokens_176.png",
    "Name": "Tokens_176.png",
    "Type": 1
  },
  {
    "ID": "RkLgkR/XFsYdcQHmuCaGNw==",
    "Path": "save:Resource/Images/Tokens_177.png",
    "Name": "Tokens_177.png",
    "Type": 1
  },
  {
    "ID": "jrq36JyJP9zqgfvfHQpaCg==",
    "Path": "save:Resource/Images/Tokens_178.png",
    "Name": "Tokens_178.png",
    "Type": 1
  },
  {
    "ID": "ZH9t80MyVNgKMksfESy2PQ==",
    "Path": "save:Resource/Images/Tokens_179.png",
    "Name": "Tokens_179.png",
    "Type": 1
  },
  {
    "ID": "MCNu30KyMhYLg+OnaJ4X4g==",
    "Path": "save:Resource/Images/Tokens_180.png",
    "Name": "Tokens_180.png",
    "Type": 1
  },
  {
    "ID": "9ctY8bNfb+xAZQTMyjOXCw==",
    "Path": "save:Resource/Images/Tokens_181.png",
    "Name": "Tokens_181.png",
    "Type": 1
  },
  {
    "ID": "dOpDmhuGRyds5r0WBUxN0w==",
    "Path": "save:Resource/Images/Tokens_181_Ampharos_MEGA.png",
    "Name": "Tokens_181_Ampharos_MEGA.png",
    "Type": 1
  },
  {
    "ID": "WyQakiMb4IKFj4PvWuMi+g==",
    "Path": "save:Resource/Images/Tokens_182.png",
    "Name": "Tokens_182.png",
    "Type": 1
  },
  {
    "ID": "S0gUdrQwb7WBGTdZ7mrbIA==",
    "Path": "save:Resource/Images/Tokens_183.png",
    "Name": "Tokens_183.png",
    "Type": 1
  },
  {
    "ID": "4RugStTgmiiiT1qlFf8zWQ==",
    "Path": "save:Resource/Images/Tokens_184.png",
    "Name": "Tokens_184.png",
    "Type": 1
  },
  {
    "ID": "Xg7o4pMrxInrqEihAIAdUw==",
    "Path": "save:Resource/Images/Tokens_185.png",
    "Name": "Tokens_185.png",
    "Type": 1
  },
  {
    "ID": "aAV/XGNQ5N2j6wYOvLhCnQ==",
    "Path": "save:Resource/Images/Tokens_186.png",
    "Name": "Tokens_186.png",
    "Type": 1
  },
  {
    "ID": "ZWT1WSEOQ2nYR/JiiIgNdA==",
    "Path": "save:Resource/Images/Tokens_187.png",
    "Name": "Tokens_187.png",
    "Type": 1
  },
  {
    "ID": "sjtzIYv664DPuLII9T1VTQ==",
    "Path": "save:Resource/Images/Tokens_188.png",
    "Name": "Tokens_188.png",
    "Type": 1
  },
  {
    "ID": "jOuoMiC3J/us95EPssd0uA==",
    "Path": "save:Resource/Images/Tokens_189.png",
    "Name": "Tokens_189.png",
    "Type": 1
  },
  {
    "ID": "ntKpj25eyb4TPyyn0Udg/Q==",
    "Path": "save:Resource/Images/Tokens_190.png",
    "Name": "Tokens_190.png",
    "Type": 1
  },
  {
    "ID": "DjquN1yCGkyGVw4vePfEwg==",
    "Path": "save:Resource/Images/Tokens_191.png",
    "Name": "Tokens_191.png",
    "Type": 1
  },
  {
    "ID": "UufjGWWxcG1dSks7OOoULw==",
    "Path": "save:Resource/Images/Tokens_192.png",
    "Name": "Tokens_192.png",
    "Type": 1
  },
  {
    "ID": "0kPXyRosTGrHQoIleslxbw==",
    "Path": "save:Resource/Images/Tokens_193.png",
    "Name": "Tokens_193.png",
    "Type": 1
  },
  {
    "ID": "TBJaPTvlnfIPcNtgLNY56w==",
    "Path": "save:Resource/Images/Tokens_194.png",
    "Name": "Tokens_194.png",
    "Type": 1
  },
  {
    "ID": "LNUeE7yrYFNSxREbCdYv+A==",
    "Path": "save:Resource/Images/Tokens_195.png",
    "Name": "Tokens_195.png",
    "Type": 1
  },
  {
    "ID": "3I+wzTAXaxxPOIyB4hn2Mg==",
    "Path": "save:Resource/Images/Tokens_196.png",
    "Name": "Tokens_196.png",
    "Type": 1
  },
  {
    "ID": "grPbi4j9KEKQIUd9KrvGoQ==",
    "Path": "save:Resource/Images/Tokens_197.png",
    "Name": "Tokens_197.png",
    "Type": 1
  },
  {
    "ID": "QAhcNktF0yhV1t3DJVfpbQ==",
    "Path": "save:Resource/Images/Tokens_198.png",
    "Name": "Tokens_198.png",
    "Type": 1
  },
  {
    "ID": "v+4YetIMVSgKUCHESG2yFQ==",
    "Path": "save:Resource/Images/Tokens_199.png",
    "Name": "Tokens_199.png",
    "Type": 1
  },
  {
    "ID": "La6o2dK8iLB7BHHKhWvNmw==",
    "Path": "save:Resource/Images/Tokens_200.png",
    "Name": "Tokens_200.png",
    "Type": 1
  },
  {
    "ID": "AMArAV2VFOl4ymnl3DvTtA==",
    "Path": "save:Resource/Images/Tokens_201.png",
    "Name": "Tokens_201.png",
    "Type": 1
  },
  {
    "ID": "PS+nAyUZ5a51ksQ0zolBOg==",
    "Path": "save:Resource/Images/Tokens_202.png",
    "Name": "Tokens_202.png",
    "Type": 1
  },
  {
    "ID": "lCzb0RMSJpBCfMZh6j37kg==",
    "Path": "save:Resource/Images/Tokens_203.png",
    "Name": "Tokens_203.png",
    "Type": 1
  },
  {
    "ID": "NPG4cMBCLhDBDtBF0ODB1A==",
    "Path": "save:Resource/Images/Tokens_204.png",
    "Name": "Tokens_204.png",
    "Type": 1
  },
  {
    "ID": "OwvmVcX1WzcXtrRy5QWsow==",
    "Path": "save:Resource/Images/Tokens_205.png",
    "Name": "Tokens_205.png",
    "Type": 1
  },
  {
    "ID": "SH3zZgVU9FaHQ59lltRpiQ==",
    "Path": "save:Resource/Images/Tokens_206.png",
    "Name": "Tokens_206.png",
    "Type": 1
  },
  {
    "ID": "YiaWmOJ0jwnRiamdBYXXeA==",
    "Path": "save:Resource/Images/Tokens_207.png",
    "Name": "Tokens_207.png",
    "Type": 1
  },
  {
    "ID": "/xRnLqNF+sZutbB+zceW+w==",
    "Path": "save:Resource/Images/Tokens_208.png",
    "Name": "Tokens_208.png",
    "Type": 1
  },
  {
    "ID": "4G9D2RQ3Wf4xdsfZSIKeNg==",
    "Path": "save:Resource/Images/Tokens_209.png",
    "Name": "Tokens_209.png",
    "Type": 1
  },
  {
    "ID": "wzkffmVg8820VZyeCeVP+g==",
    "Path": "save:Resource/Images/Tokens_210.png",
    "Name": "Tokens_210.png",
    "Type": 1
  },
  {
    "ID": "z9LfDCNRQVznooN683u9jA==",
    "Path": "save:Resource/Images/Tokens_211.png",
    "Name": "Tokens_211.png",
    "Type": 1
  },
  {
    "ID": "pNRVcbsaK9SW3sCe/VTQ/A==",
    "Path": "save:Resource/Images/Tokens_212.png",
    "Name": "Tokens_212.png",
    "Type": 1
  },
  {
    "ID": "7QZN1LZt3/yOhANgKg0y5A==",
    "Path": "save:Resource/Images/Tokens_212_Scizor_MEGA.png",
    "Name": "Tokens_212_Scizor_MEGA.png",
    "Type": 1
  },
  {
    "ID": "mojv7XoO4TWstOOWVEaIYQ==",
    "Path": "save:Resource/Images/Tokens_213.png",
    "Name": "Tokens_213.png",
    "Type": 1
  },
  {
    "ID": "bI2ICk92ywr38QkTSvBdkw==",
    "Path": "save:Resource/Images/Tokens_214.png",
    "Name": "Tokens_214.png",
    "Type": 1
  },
  {
    "ID": "C/B6InlP8+OIYJRxoFcEIg==",
    "Path": "save:Resource/Images/Tokens_214_Heracross_MEGA.png",
    "Name": "Tokens_214_Heracross_MEGA.png",
    "Type": 1
  },
  {
    "ID": "ib9RhXK9yn6PKDAo4gUQFQ==",
    "Path": "save:Resource/Images/Tokens_215.png",
    "Name": "Tokens_215.png",
    "Type": 1
  },
  {
    "ID": "J01Gzar3/fuy5aYQBX/16g==",
    "Path": "save:Resource/Images/Tokens_216.png",
    "Name": "Tokens_216.png",
    "Type": 1
  },
  {
    "ID": "mR5KxX1gtavoi/bdkQrl8g==",
    "Path": "save:Resource/Images/Tokens_217.png",
    "Name": "Tokens_217.png",
    "Type": 1
  },
  {
    "ID": "T5Ey3656293/WQ7mjwWIfA==",
    "Path": "save:Resource/Images/Tokens_218.png",
    "Name": "Tokens_218.png",
    "Type": 1
  },
  {
    "ID": "hnouAlIQKVzvX+cqTUdRxg==",
    "Path": "save:Resource/Images/Tokens_219.png",
    "Name": "Tokens_219.png",
    "Type": 1
  },
  {
    "ID": "HVWtRAs4Aa6m9J17zcjGng==",
    "Path": "save:Resource/Images/Tokens_220.png",
    "Name": "Tokens_220.png",
    "Type": 1
  },
  {
    "ID": "HVPEovxGCz6INwBy9lmK8A==",
    "Path": "save:Resource/Images/Tokens_221.png",
    "Name": "Tokens_221.png",
    "Type": 1
  },
  {
    "ID": "lZV+Zog9hkNRnMW/vfbAsw==",
    "Path": "save:Resource/Images/Tokens_222.png",
    "Name": "Tokens_222.png",
    "Type": 1
  },
  {
    "ID": "q/yE6rYserEsgOMCGXeAfA==",
    "Path": "save:Resource/Images/Tokens_223.png",
    "Name": "Tokens_223.png",
    "Type": 1
  },
  {
    "ID": "EybTjuJb/ZxWfF4lGJVaOg==",
    "Path": "save:Resource/Images/Tokens_224.png",
    "Name": "Tokens_224.png",
    "Type": 1
  },
  {
    "ID": "PHsyoCIQrP1aOOxYkS/wQg==",
    "Path": "save:Resource/Images/Tokens_225.png",
    "Name": "Tokens_225.png",
    "Type": 1
  },
  {
    "ID": "IFC+OiYBVNkGKE7wb6Ls4g==",
    "Path": "save:Resource/Images/Tokens_226.png",
    "Name": "Tokens_226.png",
    "Type": 1
  },
  {
    "ID": "gbY81KPeSQgGQj+qhz+NGQ==",
    "Path": "save:Resource/Images/Tokens_227.png",
    "Name": "Tokens_227.png",
    "Type": 1
  },
  {
    "ID": "z5H5qrRyHjiA3KpixekVLA==",
    "Path": "save:Resource/Images/Tokens_228.png",
    "Name": "Tokens_228.png",
    "Type": 1
  },
  {
    "ID": "OAiqWVU5RLpGrKoLPOIc9g==",
    "Path": "save:Resource/Images/Tokens_229.png",
    "Name": "Tokens_229.png",
    "Type": 1
  },
  {
    "ID": "r6Mg1mXHtmQgPe+stn6BsQ==",
    "Path": "save:Resource/Images/Tokens_229_Houndoom_MEGA.png",
    "Name": "Tokens_229_Houndoom_MEGA.png",
    "Type": 1
  },
  {
    "ID": "Fg+XHOy3ZXXvTnQOdg7SqA==",
    "Path": "save:Resource/Images/Tokens_230.png",
    "Name": "Tokens_230.png",
    "Type": 1
  },
  {
    "ID": "cBBClC5uw9G/H69YJ6cfXA==",
    "Path": "save:Resource/Images/Tokens_231.png",
    "Name": "Tokens_231.png",
    "Type": 1
  },
  {
    "ID": "UJHP5T3W+Q7sJP1VdCcGwQ==",
    "Path": "save:Resource/Images/Tokens_232.png",
    "Name": "Tokens_232.png",
    "Type": 1
  },
  {
    "ID": "8+fk536MuMXQw+yJtl4M0w==",
    "Path": "save:Resource/Images/Tokens_233.png",
    "Name": "Tokens_233.png",
    "Type": 1
  },
  {
    "ID": "0mNIXvPJmLODNVGxuvRKLg==",
    "Path": "save:Resource/Images/Tokens_234.png",
    "Name": "Tokens_234.png",
    "Type": 1
  },
  {
    "ID": "t/fKRzTFkGf6Dq0e5UuNEw==",
    "Path": "save:Resource/Images/Tokens_235.png",
    "Name": "Tokens_235.png",
    "Type": 1
  },
  {
    "ID": "645+9qhtdrwxQl7Xmbdtrw==",
    "Path": "save:Resource/Images/Tokens_236.png",
    "Name": "Tokens_236.png",
    "Type": 1
  },
  {
    "ID": "cuA3ak6hb1T5pfDIiOGqvA==",
    "Path": "save:Resource/Images/Tokens_237.png",
    "Name": "Tokens_237.png",
    "Type": 1
  },
  {
    "ID": "JysupNDXhR6rsae9SHI4/w==",
    "Path": "save:Resource/Images/Tokens_238.png",
    "Name": "Tokens_238.png",
    "Type": 1
  },
  {
    "ID": "CUb5CKPgO/9saTUcP14iqw==",
    "Path": "save:Resource/Images/Tokens_239.png",
    "Name": "Tokens_239.png",
    "Type": 1
  },
  {
    "ID": "SN6Nhr3x9F/avlb1nqLWiA==",
    "Path": "save:Resource/Images/Tokens_240.png",
    "Name": "Tokens_240.png",
    "Type": 1
  },
  {
    "ID": "25+1utFOHRQ0Y5z2B+ilPg==",
    "Path": "save:Resource/Images/Tokens_241.png",
    "Name": "Tokens_241.png",
    "Type": 1
  },
  {
    "ID": "+Dnv2DmsIGzP+PcgFHSjsw==",
    "Path": "save:Resource/Images/Tokens_242.png",
    "Name": "Tokens_242.png",
    "Type": 1
  },
  {
    "ID": "T8NiVC9Z68io2DhhnZpHKQ==",
    "Path": "save:Resource/Images/Tokens_243.png",
    "Name": "Tokens_243.png",
    "Type": 1
  },
  {
    "ID": "TJ72IF8XcLBNu+HH3gPoiw==",
    "Path": "save:Resource/Images/Tokens_244.png",
    "Name": "Tokens_244.png",
    "Type": 1
  },
  {
    "ID": "YsHYFEZGK3Y6e3iwUCMrZQ==",
    "Path": "save:Resource/Images/Tokens_245.png",
    "Name": "Tokens_245.png",
    "Type": 1
  },
  {
    "ID": "tPG71W0UhlLooEoOOCirLA==",
    "Path": "save:Resource/Images/Tokens_246.png",
    "Name": "Tokens_246.png",
    "Type": 1
  },
  {
    "ID": "MKz+QIGxEy15BOFl4id28g==",
    "Path": "save:Resource/Images/Tokens_247.png",
    "Name": "Tokens_247.png",
    "Type": 1
  },
  {
    "ID": "Kgv7fzLzGhBvkcksu9ybJQ==",
    "Path": "save:Resource/Images/Tokens_248.png",
    "Name": "Tokens_248.png",
    "Type": 1
  },
  {
    "ID": "Hy4tbWohra+bY6+73dEOMw==",
    "Path": "save:Resource/Images/Tokens_248_Tyranitar_MEGA.png",
    "Name": "Tokens_248_Tyranitar_MEGA.png",
    "Type": 1
  },
  {
    "ID": "O3Um0TUu2n7m+DQiO/f/Lw==",
    "Path": "save:Resource/Images/Tokens_249.png",
    "Name": "Tokens_249.png",
    "Type": 1
  },
  {
    "ID": "CrQj/bymeUyK2wwFT0YY4w==",
    "Path": "save:Resource/Images/Tokens_250.png",
    "Name": "Tokens_250.png",
    "Type": 1
  },
  {
    "ID": "m/e8OpBCM7k6Ro/BETWlwA==",
    "Path": "save:Resource/Images/Tokens_251.png",
    "Name": "Tokens_251.png",
    "Type": 1
  },
  {
    "ID": "fV/S4a41krZyJxrhHpXpPg==",
    "Path": "save:Resource/Images/Tokens_ghost.png",
    "Name": "Tokens_ghost.png",
    "Type": 1
  },
  {
    "ID": "3VBVhqmHPWEjFxZUXCwyNA==",
    "Path": "save:Resource/Images/TypeIcon_bug.png",
    "Name": "TypeIcon_bug.png",
    "Type": 1
  },
  {
    "ID": "joY95tIg81HnHmiN4Iv4tA==",
    "Path": "save:Resource/Images/TypeIcon_dark.png",
    "Name": "TypeIcon_dark.png",
    "Type": 1
  },
  {
    "ID": "UlQAQVUypSA+3sChGkxVhQ==",
    "Path": "save:Resource/Images/TypeIcon_dragon.png",
    "Name": "TypeIcon_dragon.png",
    "Type": 1
  },
  {
    "ID": "JRDp213CfIqsKc6E/X7IGw==",
    "Path": "save:Resource/Images/TypeIcon_electric.png",
    "Name": "TypeIcon_electric.png",
    "Type": 1
  },
  {
    "ID": "oI58yzLoj5jZmvXnN+2EvQ==",
    "Path": "save:Resource/Images/TypeIcon_fairy.png",
    "Name": "TypeIcon_fairy.png",
    "Type": 1
  },
  {
    "ID": "zXmcYgRQPVxfbf/tzT0wlg==",
    "Path": "save:Resource/Images/TypeIcon_fighting.png",
    "Name": "TypeIcon_fighting.png",
    "Type": 1
  },
  {
    "ID": "t67UnJfy9lwvU2bqHNgmOA==",
    "Path": "save:Resource/Images/TypeIcon_fire.png",
    "Name": "TypeIcon_fire.png",
    "Type": 1
  },
  {
    "ID": "Pvxt8jL0rWLrbd3l0jYCNw==",
    "Path": "save:Resource/Images/TypeIcon_flying.png",
    "Name": "TypeIcon_flying.png",
    "Type": 1
  },
  {
    "ID": "t2N7jWcB3iHFp6O9U0kBlw==",
    "Path": "save:Resource/Images/TypeIcon_ghost.png",
    "Name": "TypeIcon_ghost.png",
    "Type": 1
  },
  {
    "ID": "1tINHNvxz98UwWCAR99T/A==",
    "Path": "save:Resource/Images/TypeIcon_grass.png",
    "Name": "TypeIcon_grass.png",
    "Type": 1
  },
  {
    "ID": "65tE3PJbGml7N4kRbJKU3Q==",
    "Path": "save:Resource/Images/TypeIcon_ground.png",
    "Name": "TypeIcon_ground.png",
    "Type": 1
  },
  {
    "ID": "/tuSWdKq6MKRXm3I7pJ8yw==",
    "Path": "save:Resource/Images/TypeIcon_ice.png",
    "Name": "TypeIcon_ice.png",
    "Type": 1
  },
  {
    "ID": "nPdyLOJLzDWqTswpYS+/3g==",
    "Path": "save:Resource/Images/TypeIcon_normal.png",
    "Name": "TypeIcon_normal.png",
    "Type": 1
  },
  {
    "ID": "DRNfomQdtTawRHgISjVGXA==",
    "Path": "save:Resource/Images/TypeIcon_poison.png",
    "Name": "TypeIcon_poison.png",
    "Type": 1
  },
  {
    "ID": "M2VE1Qr5gu1tBoU9jH1Ncw==",
    "Path": "save:Resource/Images/TypeIcon_psycic.png",
    "Name": "TypeIcon_psycic.png",
    "Type": 1
  },
  {
    "ID": "lE5h4CigbB5aOZVetafLWw==",
    "Path": "save:Resource/Images/TypeIcon_rock.png",
    "Name": "TypeIcon_rock.png",
    "Type": 1
  },
  {
    "ID": "Gz+hPt/yDVz/1sr6iJ+cBw==",
    "Path": "save:Resource/Images/TypeIcon_steel.png",
    "Name": "TypeIcon_steel.png",
    "Type": 1
  },
  {
    "ID": "nOhzXvEqtYEe3uvE8pWI6Q==",
    "Path": "save:Resource/Images/TypeIcon_water.png",
    "Name": "TypeIcon_water.png",
    "Type": 1
  }
]
